depends/__init__.py
depends/dependable.py
depends/dependencies.py
depends/depends.py
depends/inject.py
python_depends-0.1.4.dist-info/WHEEL
python_depends-0.1.4.dist-info/METADATA
python_depends-0.1.4.dist-info/RECORD
